LICENSE
simple_github_crawler/__init__.py
simple_github_crawler/commit.py
simple_github_crawler-0.2.1.dist-info/LICENSE
simple_github_crawler-0.2.1.dist-info/WHEEL
simple_github_crawler-0.2.1.dist-info/METADATA
simple_github_crawler-0.2.1.dist-info/RECORD
